{"framework_introduce.md":"jxySBSJJ","framework_vite.md":"ywRqEPvv","faq_readme.md":"yG22e6IY","framework_index.md":"AR-XJTjv","index.md":"xGW5LrqN","framework_react.md":"Hn5KrR6g","guide_static-source.md":"4Gnf07qb","guide_keep-alive.md":"9eBRivVz","guide_browser-router.md":"uVxgpReb","framework_nuxtjs.md":"KXakfV2G","framework_nextjs.md":"y-VsrJfH","framework_angular.md":"bVaQt2y7","framework_vue.md":"j9oIP8p3","guide_index.md":"64efJRiz","guide_data.md":"TxoEyQbe","guide_router.md":"gcU570hs","api_index.md":"M0V97Jf9"}
